imagedata_format_ps/__init__.py
imagedata_format_ps/psplugin.py
imagedata_format_ps-0.0.2.dist-info/LICENSE.txt
imagedata_format_ps-0.0.2.dist-info/METADATA
imagedata_format_ps-0.0.2.dist-info/WHEEL
imagedata_format_ps-0.0.2.dist-info/entry_points.txt
imagedata_format_ps-0.0.2.dist-info/top_level.txt
imagedata_format_ps-0.0.2.dist-info/RECORD
